{
  "data": {
    "greenerNightsForecast": [
      {
        "date": "2026-02-22",
        "greennessScore": 85,
        "isGreenerNight": true,
        "greennessIndex": "HIGH",
        "wasGreenerNight": true
      },
      {
        "date": "2026-02-23",
        "greennessScore": 54,
        "isGreenerNight": false,
        "greennessIndex": "MEDIUM",
        "wasGreenerNight": false
      },
      {
        "date": "2026-02-24",
        "greennessScore": 65,
        "isGreenerNight": false,
        "greennessIndex": "MEDIUM",
        "wasGreenerNight": false
      },
      {
        "date": "2026-02-25",
        "greennessScore": 62,
        "isGreenerNight": false,
        "greennessIndex": "MEDIUM",
        "wasGreenerNight": false
      },
      {
        "date": "2026-02-26",
        "greennessScore": 81,
        "isGreenerNight": false,
        "greennessIndex": "HIGH",
        "wasGreenerNight": false
      },
      {
        "date": "2026-02-27",
        "greennessScore": 67,
        "isGreenerNight": false,
        "greennessIndex": "HIGH",
        "wasGreenerNight": false
      },
      {
        "date": "2026-02-28",
        "greennessScore": 61,
        "isGreenerNight": false,
        "greennessIndex": "MEDIUM",
        "wasGreenerNight": false
      }
    ]
  }
}
