{
  "data": {
    "greenerNightsForecast": [
      {
        "date": "2026-05-24",
        "greennessScore": 21,
        "isGreenerNight": false,
        "greennessIndex": "LOW",
        "wasGreenerNight": true
      },
      {
        "date": "2026-05-25",
        "greennessScore": 30,
        "isGreenerNight": false,
        "greennessIndex": "LOW",
        "wasGreenerNight": true
      },
      {
        "date": "2026-05-26",
        "greennessScore": 26,
        "isGreenerNight": false,
        "greennessIndex": "LOW",
        "wasGreenerNight": false
      },
      {
        "date": "2026-05-27",
        "greennessScore": 29,
        "isGreenerNight": false,
        "greennessIndex": "LOW",
        "wasGreenerNight": false
      },
      {
        "date": "2026-05-28",
        "greennessScore": 35,
        "isGreenerNight": true,
        "greennessIndex": "MEDIUM",
        "wasGreenerNight": true
      },
      {
        "date": "2026-05-29",
        "greennessScore": 25,
        "isGreenerNight": false,
        "greennessIndex": "LOW",
        "wasGreenerNight": true
      },
      {
        "date": "2026-05-30",
        "greennessScore": 34,
        "isGreenerNight": true,
        "greennessIndex": "MEDIUM",
        "wasGreenerNight": true
      }
    ]
  }
}
