{
  "data": {
    "greenerNightsForecast": [
      {
        "date": "2026-06-24",
        "greennessScore": 15,
        "isGreenerNight": false,
        "greennessIndex": "LOW",
        "wasGreenerNight": false
      },
      {
        "date": "2026-06-25",
        "greennessScore": 55,
        "isGreenerNight": true,
        "greennessIndex": "MEDIUM",
        "wasGreenerNight": true
      },
      {
        "date": "2026-06-26",
        "greennessScore": 26,
        "isGreenerNight": false,
        "greennessIndex": "LOW",
        "wasGreenerNight": true
      },
      {
        "date": "2026-06-27",
        "greennessScore": 38,
        "isGreenerNight": false,
        "greennessIndex": "MEDIUM",
        "wasGreenerNight": false
      },
      {
        "date": "2026-06-28",
        "greennessScore": 34,
        "isGreenerNight": false,
        "greennessIndex": "MEDIUM",
        "wasGreenerNight": false
      },
      {
        "date": "2026-06-29",
        "greennessScore": 11,
        "isGreenerNight": false,
        "greennessIndex": "LOW",
        "wasGreenerNight": false
      },
      {
        "date": "2026-06-30",
        "greennessScore": 23,
        "isGreenerNight": false,
        "greennessIndex": "LOW",
        "wasGreenerNight": false
      }
    ]
  }
}
